<?xml version='1.0' encoding='us-ascii'?>
<annotation>
	<folder>JPEGImages</folder>
	<filename>exp6_num_4841.jpg</filename>
	<path>C:\Users\chenz\Desktop\ciwa&#65288;&#24050;&#36716;xml&#65289;base\MT_Blowhole\JPEGImages\exp6_num_4841.jpg</path>
	<source>
		<database>Unknown</database>
	</source>
	<size>
		<width>122</width>
		<height>288</height>
		<depth>1</depth>
	</size>
	<segmented>0</segmented>
	<object>
		<name>blowhole</name>
		<pose>Unspecified</pose>
		<truncated>0</truncated>
		<difficult>0</difficult>
		<bndbox>
			<xmin>18</xmin>
			<ymin>257</ymin>
			<xmax>41</xmax>
			<ymax>276</ymax>
		</bndbox>
	</object>
</annotation>